setup_utils/LICENSE.apache-2.0
setup_utils/__init__.py
setup_utils-0.2.0.dist-info/LICENSE
setup_utils-0.2.0.dist-info/WHEEL
setup_utils-0.2.0.dist-info/METADATA
setup_utils-0.2.0.dist-info/RECORD
