Metadata-Version: 2.1
Name: setup-utils
Version: 0.2.0
Summary: Python Setup Utilities
License: MIT
Author: skeptycal
Author-email: 26148512+skeptycal@users.noreply.github.com
Requires-Python: >=3.8,<4.0
Classifier: License :: OSI Approved :: MIT License
Classifier: Programming Language :: Python :: 3
Classifier: Programming Language :: Python :: 3.8
